resokerr/__init__.py
resokerr/core.py
resokerr-1.1.0.dist-info/licenses/LICENSE
tests/__init__.py
tests/test_edge_cases.py
tests/test_err.py
tests/test_map.py
tests/test_message_trace.py
tests/test_ok.py
tests/test_pattern_matching.py
tests/test_result_composition.py
tests/test_serialization.py
tests/test_unwrap.py
resokerr-1.1.0.dist-info/METADATA
resokerr-1.1.0.dist-info/WHEEL
resokerr-1.1.0.dist-info/top_level.txt
resokerr-1.1.0.dist-info/RECORD
