Metadata-Version: 2.4
Name: resokerr
Version: 1.1.0
Summary: A Python library for simple Result/Ok/Err return types with rich message tracing and metadata support.
Author-email: Picurit <dev@picurit.com>
License-Expression: MIT
Project-URL: Repository, https://github.com/picurit/py-resokerr
Project-URL: Issues, https://github.com/picurit/py-resokerr/issues
Project-URL: Changelog, https://github.com/picurit/py-resokerr/blob/main/CHANGELOG.md
Classifier: Programming Language :: Python :: 3.11
Classifier: Operating System :: OS Independent
Requires-Python: >=3.11
License-File: LICENSE
Dynamic: license-file
